{
  "name": "applgrid",
  "full_name": "davidchall/hep/applgrid",
  "tap": "davidchall/hep",
  "oldname": null,
  "aliases": [

  ],
  "versioned_formulae": [

  ],
  "desc": "Quickly reproduce NLO calculations with any input PDFs",
  "license": "GPL-3.0-only",
  "homepage": "https://applgrid.hepforge.org",
  "versions": {
    "stable": "1.6.28",
    "head": null,
    "bottle": true
  },
  "urls": {
    "stable": {
      "url": "https://applgrid.hepforge.org/downloads?f=applgrid-1.6.28.tgz",
      "tag": null,
      "revision": null
    }
  },
  "revision": 0,
  "version_scheme": 0,
  "bottle": {
    "stable": {
      "rebuild": 0,
      "root_url": "https://ghcr.io/v2/davidchall/hep",
      "files": {
        "monterey": {
          "cellar": ":any",
          "url": "https://ghcr.io/v2/davidchall/hep/applgrid/blobs/sha256:b2e7cc54c0371d649ab23120eb916239ead89004de77e0e345cfaf1c5d963a60",
          "sha256": "b2e7cc54c0371d649ab23120eb916239ead89004de77e0e345cfaf1c5d963a60"
        },
        "big_sur": {
          "cellar": ":any",
          "url": "https://ghcr.io/v2/davidchall/hep/applgrid/blobs/sha256:dd2847ec25410db823b7e02ef8c3b4e6b9ea911a6c867bc90bb4d8547d926a1a",
          "sha256": "dd2847ec25410db823b7e02ef8c3b4e6b9ea911a6c867bc90bb4d8547d926a1a"
        },
        "catalina": {
          "cellar": ":any",
          "url": "https://ghcr.io/v2/davidchall/hep/applgrid/blobs/sha256:11bad5decf5f98bb6341bc16c576e662e788d170076591e1576e974d99d07af4",
          "sha256": "11bad5decf5f98bb6341bc16c576e662e788d170076591e1576e974d99d07af4"
        }
      }
    }
  },
  "keg_only": false,
  "keg_only_reason": null,
  "options": [
    {
      "option": "--without-hoppet",
      "description": "Build without hoppet support"
    },
    {
      "option": "--without-lhapdf",
      "description": "Build without lhapdf support"
    },
    {
      "option": "--without-root",
      "description": "Build without root support"
    }
  ],
  "build_dependencies": [

  ],
  "dependencies": [
    "gcc"
  ],
  "recommended_dependencies": [
    "hoppet",
    "lhapdf",
    "root"
  ],
  "optional_dependencies": [

  ],
  "uses_from_macos": [

  ],
  "requirements": [

  ],
  "conflicts_with": [

  ],
  "caveats": null,
  "installed": [

  ],
  "linked_keg": null,
  "pinned": false,
  "outdated": false,
  "deprecated": false,
  "deprecation_date": null,
  "deprecation_reason": null,
  "disabled": false,
  "disable_date": null,
  "disable_reason": null
}
